TensorFI/__init__.py
TensorFI/faultTypes.py
TensorFI/fiConfig.py
TensorFI/fiLog.py
TensorFI/fiStats.py
TensorFI/injectFault.py
TensorFI/modifyGraph.py
TensorFI/printGraph.py
TensorFI/tensorFI.py
TensorFI-2.0.0.dist-info/LICENSE
TensorFI-2.0.0.dist-info/METADATA
TensorFI-2.0.0.dist-info/WHEEL
TensorFI-2.0.0.dist-info/top_level.txt
TensorFI-2.0.0.dist-info/RECORD
